[
  {
    "bbox": {
      "x1": 142.0,
      "y1": 46.0,
      "x2": 197.0,
      "y2": 100.0
    },
    "label": 0
  },
  {
    "bbox": {
      "x1": 74.0,
      "y1": 38.0,
      "x2": 113.0,
      "y2": 68.0
    },
    "label": 2
  },
  {
    "bbox": {
      "x1": 17.0,
      "y1": 183.0,
      "x2": 81.0,
      "y2": 242.0
    },
    "label": 1
  },
  {
    "bbox": {
      "x1": 37.0,
      "y1": 13.0,
      "x2": 65.0,
      "y2": 49.0
    },
    "label": 3
  },
  {
    "bbox": {
      "x1": 62.0,
      "y1": 124.0,
      "x2": 116.0,
      "y2": 196.0
    },
    "label": 4
  },
  {
    "bbox": {
      "x1": 91.0,
      "y1": 53.0,
      "x2": 151.0,
      "y2": 111.0
    },
    "label": 4
  },
  {
    "bbox": {
      "x1": 111.0,
      "y1": 99.0,
      "x2": 176.0,
      "y2": 166.0
    },
    "label": 1
  },
  {
    "bbox": {
      "x1": 223.0,
      "y1": 144.0,
      "x2": 249.0,
      "y2": 161.0
    },
    "label": 2
  },
  {
    "bbox": {
      "x1": 185.0,
      "y1": 184.0,
      "x2": 224.0,
      "y2": 225.0
    },
    "label": 4
  }
]