[
  {
    "bbox": {
      "x1": 165.0,
      "y1": 104.0,
      "x2": 201.0,
      "y2": 150.0
    },
    "label": 3
  },
  {
    "bbox": {
      "x1": 36.0,
      "y1": 40.0,
      "x2": 93.0,
      "y2": 103.0
    },
    "label": 2
  },
  {
    "bbox": {
      "x1": 68.0,
      "y1": 98.0,
      "x2": 110.0,
      "y2": 134.0
    },
    "label": 2
  },
  {
    "bbox": {
      "x1": 95.0,
      "y1": 146.0,
      "x2": 124.0,
      "y2": 182.0
    },
    "label": 3
  },
  {
    "bbox": {
      "x1": 197.0,
      "y1": 201.0,
      "x2": 227.0,
      "y2": 230.0
    },
    "label": 0
  },
  {
    "bbox": {
      "x1": 116.0,
      "y1": 188.0,
      "x2": 152.0,
      "y2": 231.0
    },
    "label": 4
  }
]