[
  {
    "bbox": {
      "x1": 66.0,
      "y1": 217.0,
      "x2": 89.0,
      "y2": 240.0
    },
    "label": 4
  },
  {
    "bbox": {
      "x1": 81.0,
      "y1": 32.0,
      "x2": 158.0,
      "y2": 127.0
    },
    "label": 4
  },
  {
    "bbox": {
      "x1": 138.0,
      "y1": 183.0,
      "x2": 186.0,
      "y2": 236.0
    },
    "label": 2
  },
  {
    "bbox": {
      "x1": 117.0,
      "y1": 142.0,
      "x2": 146.0,
      "y2": 181.0
    },
    "label": 3
  },
  {
    "bbox": {
      "x1": 188.0,
      "y1": 178.0,
      "x2": 220.0,
      "y2": 210.0
    },
    "label": 0
  },
  {
    "bbox": {
      "x1": 138.0,
      "y1": 42.0,
      "x2": 201.0,
      "y2": 104.0
    },
    "label": 2
  },
  {
    "bbox": {
      "x1": 152.0,
      "y1": 95.0,
      "x2": 194.0,
      "y2": 142.0
    },
    "label": 3
  },
  {
    "bbox": {
      "x1": 33.0,
      "y1": 102.0,
      "x2": 101.0,
      "y2": 181.0
    },
    "label": 1
  }
]